{
  "id": 890,
  "slug": "akvamarin-890",
  "name": "Аквамарин",
  "phone": "+7 916 6067100",
  "phone_display": "+7 916 6067100",
  "address": null,
  "city": "Москва",
  "metro_nearest": null,
  "niche": "Автомойки",
  "yandex_url": "https://yandex.ru/maps/org/akvamarin/74278242073/",
  "rating": 4.7,
  "reviews_count": 270,
  "ratings_count": 560,
  "hours": {
    "is_24_7": false,
    "structured": {}
  },
  "geo": {
    "lat": 55.784883,
    "lon": 37.6120212
  },
  "photos_count": 12,
  "photos_downloaded": 12,
  "description_short": "Аквамарин — Автомойки в Москве, рейтинг 4.7",
  "description_long": null,
  "social": {},
  "services": [],
  "services_count": 0,
  "features": [],
  "enrichment_sources": [
    "osm",
    "yandex_maps"
  ],
  "enriched_at": "2026-06-19T02:24:22",
  "completeness_score": 0.75
}